asap_stereo/__init__.py
asap_stereo/asap.py
asap_stereo/asap_ctx_workflow.ipynb
asap_stereo/asap_hirise_workflow.ipynb
asap_stereo/asap_hirise_workflow_hiproc.ipynb
asap_stereo/asap_hirise_workflow_nomap.ipynb
asap_stereo/stereo_quality.py
asap_stereo-0.3.1.dist-info/LICENSE
asap_stereo-0.3.1.dist-info/METADATA
asap_stereo-0.3.1.dist-info/WHEEL
asap_stereo-0.3.1.dist-info/entry_points.txt
asap_stereo-0.3.1.dist-info/top_level.txt
asap_stereo-0.3.1.dist-info/RECORD
