Metadata-Version: 2.1
Name: asap-stereo
Version: 0.3.1
Summary: A high level CLI and reproducible workflow for the Ames Stereo Pipeline
Author-email: "Andrew M. Annex" <ama6fy@virginia.edu>
License: BSD 3-Clause License
Project-URL: repository, https://github.com/AndrewAnnex/asap_stereo/
Keywords: mars,nasa,asp,ames,stereo,pipeline,cli,tool,workflow
Classifier: Natural Language :: English
Classifier: License :: OSI Approved :: BSD License
Classifier: Development Status :: 3 - Alpha
Classifier: Environment :: Console
Classifier: Intended Audience :: Developers
Classifier: Intended Audience :: Science/Research
Classifier: Programming Language :: Python :: 3
Classifier: Programming Language :: Python :: 3.9
Classifier: Programming Language :: Python :: 3.10
Classifier: Programming Language :: Python :: 3.11
Classifier: Topic :: Scientific/Engineering :: Astronomy
Classifier: Topic :: Scientific/Engineering :: GIS
Requires-Python: >=3.9
License-File: LICENSE
Requires-Dist: requests
Requires-Dist: fire
Requires-Dist: moody (>=0.2.0)
Requires-Dist: sh (>=2.0.0)
Requires-Dist: papermill
Requires-Dist: rasterio
Requires-Dist: pyproj
